{
  "$schema": "https://developer.microsoft.com/json-schemas/spfx-build/package-solution.schema.json",
  "solution": {
    "name": "carved-rock-library-client-side-solution",
    "id": "aaef2e3c-92a4-48d4-a86a-81d504d4560e",
    "version": "1.0.0.0",
    "includeClientSideAssets": true,
    "skipFeatureDeployment": true,
    "isDomainIsolated": false,
    "developer": {
      "name": "",
      "websiteUrl": "",
      "privacyUrl": "",
      "termsOfUseUrl": "",
      "mpnId": ""
    }
  },
  "paths": {
    "zippedPackage": "solution/carved-rock-library.sppkg"
  }
}
